sitesyncro-0.9.7.data/purelib/sitesyncro/Model.py
sitesyncro-0.9.7.data/purelib/sitesyncro/Phase.py
sitesyncro-0.9.7.data/purelib/sitesyncro/Sample.py
sitesyncro-0.9.7.data/purelib/sitesyncro/__init__.py
sitesyncro-0.9.7.data/purelib/sitesyncro/graphviz/__init__.py
sitesyncro-0.9.7.data/purelib/sitesyncro/mhelpers/MCluster.py
sitesyncro-0.9.7.data/purelib/sitesyncro/mhelpers/MOxCal.py
sitesyncro-0.9.7.data/purelib/sitesyncro/mhelpers/MPhasing.py
sitesyncro-0.9.7.data/purelib/sitesyncro/mhelpers/MPlot.py
sitesyncro-0.9.7.data/purelib/sitesyncro/mhelpers/MRandomization.py
sitesyncro-0.9.7.data/purelib/sitesyncro/mhelpers/__init__.py
sitesyncro-0.9.7.data/purelib/sitesyncro/pygraphviz/__init__.py
sitesyncro-0.9.7.data/purelib/sitesyncro/pygraphviz/agraph.py
sitesyncro-0.9.7.data/purelib/sitesyncro/pygraphviz/graphviz.py
sitesyncro-0.9.7.data/purelib/sitesyncro/pygraphviz/scraper.py
sitesyncro-0.9.7.data/purelib/sitesyncro/pygraphviz/testing.py
sitesyncro-0.9.7.data/purelib/sitesyncro/utils/__init__.py
sitesyncro-0.9.7.data/purelib/sitesyncro/utils/fnc_cluster.py
sitesyncro-0.9.7.data/purelib/sitesyncro/utils/fnc_data.py
sitesyncro-0.9.7.data/purelib/sitesyncro/utils/fnc_load.py
sitesyncro-0.9.7.data/purelib/sitesyncro/utils/fnc_mp.py
sitesyncro-0.9.7.data/purelib/sitesyncro/utils/fnc_oxcal.py
sitesyncro-0.9.7.data/purelib/sitesyncro/utils/fnc_phase.py
sitesyncro-0.9.7.data/purelib/sitesyncro/utils/fnc_radiocarbon.py
sitesyncro-0.9.7.data/purelib/sitesyncro/utils/fnc_simulate.py
sitesyncro-0.9.7.data/purelib/sitesyncro/utils/fnc_stat.py
sitesyncro-0.9.7.data/purelib/sitesyncro/utils/fnc_visualize.py
sitesyncro-0.9.7.dist-info/LICENSE
sitesyncro-0.9.7.dist-info/METADATA
sitesyncro-0.9.7.dist-info/WHEEL
sitesyncro-0.9.7.dist-info/top_level.txt
sitesyncro-0.9.7.dist-info/RECORD
