Metadata-Version: 2.1
Name: sitesyncro
Version: 0.9.7
Summary: SiteSyncro - Site-specific chronological modeling and synchronization
Home-page: https://github.com/demjanp/SiteSyncro
Author: Peter Demjan
Author-email: peter.demjan@gmail.com
Keywords: archaeology,radiocarbon,chronology,stratigraphy
Classifier: Development Status :: 5 - Production/Stable
Classifier: Intended Audience :: Science/Research
Classifier: Topic :: Scientific/Engineering
Classifier: License :: OSI Approved :: GNU General Public License v3 (GPLv3)
Classifier: Programming Language :: Python :: 3.10
Requires-Python: >=3.10, <3.11
License-File: LICENSE
Requires-Dist: numpy <2,>=1.26.4
Requires-Dist: scipy <2,>=1.13.0
Requires-Dist: matplotlib <4,>=3.8.4
Requires-Dist: scikit-learn <2,>=1.4.2
Requires-Dist: tqdm <5,>=4.66.0
Requires-Dist: requests <3,>=2.31.0
Requires-Dist: networkx <4,>=2.8.0
Requires-Dist: sphinx <7.4,>=7.3.7
Requires-Dist: myst-parser <3.1,>=3.0.1
Requires-Dist: Pillow <10,>=9.5.0
Requires-Dist: python-pptx <1,>=0.6.23
Requires-Dist: natsort <9,>=8.4.0
